fastapi_templateapp/__init__.py
fastapi_templateapp/async_requests_manager.py
fastapi_templateapp/exceptions.py
fastapi_templateapp/security.py
fastapi_templateapp/template_app.py
fastapi_templateapp/templates/errors/base_error.html
fastapi_templateapp-0.1.6.dist-info/METADATA
fastapi_templateapp-0.1.6.dist-info/WHEEL
fastapi_templateapp-0.1.6.dist-info/top_level.txt
fastapi_templateapp-0.1.6.dist-info/RECORD
