Metadata-Version: 2.1
Name: fastapi_templateapp
Version: 0.1.6
Summary: Library for ease of working with templates
Home-page: https://github.com/comasqw/fastapi_templateapp
Author: Sevbii
Classifier: Programming Language :: Python :: 3
Classifier: License :: OSI Approved :: MIT License
Classifier: Operating System :: OS Independent
Requires-Python: >=3.6
Requires-Dist: fastapi
Requires-Dist: apscheduler
Requires-Dist: httpx
